minibib/__init__.py
minibib/minibib.py
minibib-1.0.1.dist-info/LICENSE
minibib-1.0.1.dist-info/METADATA
minibib-1.0.1.dist-info/WHEEL
minibib-1.0.1.dist-info/entry_points.txt
minibib-1.0.1.dist-info/top_level.txt
minibib-1.0.1.dist-info/RECORD
