Metadata-Version: 2.1
Name: minibib
Version: 1.0.1
Summary: A simple script to create a clean `.bib` file containing only the references cited in your `.tex` document.
Home-page: https://github.com/lmytime/minibib
Author: Mingyu Li
Author-email: lmytime@hotmail.com
License: MIT
Classifier: Programming Language :: Python :: 3
Classifier: License :: OSI Approved :: MIT License
Classifier: Operating System :: OS Independent
Requires-Python: >=3.6
License-File: LICENSE
